stouchtool/__init__.py
stouchtool/s_cat.py
stouchtool/s_plot.py
STouchTool-0.1.2.dist-info/AUTHORS.rst
STouchTool-0.1.2.dist-info/LICENSE.txt
STouchTool-0.1.2.dist-info/METADATA
STouchTool-0.1.2.dist-info/WHEEL
STouchTool-0.1.2.dist-info/entry_points.txt
STouchTool-0.1.2.dist-info/top_level.txt
STouchTool-0.1.2.dist-info/RECORD
