Metadata-Version: 2.1
Name: STouchTool
Version: 0.1.2
Summary: Collection of tools to manipulate Touchstone files
Home-page: https://github.com/jtplaarj/STouchTool
Author: Jesús Lázaro
Author-email: jesus.lazaro@ehu.eus
License: MIT
Project-URL: Documentation, https://readthedocs.org/projects/STouchTool/
Project-URL: Source, https://github.com/jtplaarj/STouchTool/
Project-URL: Changelog, https://github.com/jtplaarj/STouchTool/blob/master/CHANGELOG.rst
Project-URL: Download, https://pypi.org/project/STouchTool/#files
Platform: any
Classifier: Development Status :: 4 - Beta
Classifier: Programming Language :: Python
License-File: LICENSE.txt
License-File: AUTHORS.rst
Requires-Dist: matplotlib
Requires-Dist: numpy
Requires-Dist: scipy
Requires-Dist: scikit-rf
Requires-Dist: importlib-metadata ; python_version < "3.8"
Provides-Extra: testing
Requires-Dist: setuptools ; extra == 'testing'
Requires-Dist: pytest ; extra == 'testing'
Requires-Dist: pytest-cov ; extra == 'testing'
Requires-Dist: numpy ; extra == 'testing'
Requires-Dist: PyPDF2 ; extra == 'testing'
Requires-Dist: scikit-rf ; extra == 'testing'
